{"nodes": [{"id": "c_w_rise_rise_media_player_dev_settings_insiderpage_xaml", "label": "InsiderPage.xaml", "file_type": "code", "source_file": "Rise Media Player Dev/Settings/InsiderPage.xaml", "source_location": "L1"}, {"id": "settings_insiderpage_page", "label": "Page", "file_type": "code", "source_file": "Rise Media Player Dev/Settings/InsiderPage.xaml", "source_location": "L1"}, {"id": "settings_insiderpage_xaml_insiderpage", "label": "InsiderPage", "file_type": "code", "source_file": "Rise Media Player Dev/Settings/InsiderPage.xaml.cs", "source_location": "L10"}, {"id": "settings_insiderpage_xaml_insiderpage_expandercontrol_click", "label": ".ExpanderControl_Click()", "file_type": "code", "source_file": "Rise Media Player Dev/Settings/InsiderPage.xaml.cs", "source_location": "L17"}], "edges": [{"source": "c_w_rise_rise_media_player_dev_settings_insiderpage_xaml", "target": "settings_insiderpage_page", "relation": "contains", "confidence": "EXTRACTED", "source_file": "Rise Media Player Dev/Settings/InsiderPage.xaml", "source_location": "L1", "weight": 1.0}, {"source": "settings_insiderpage_page", "target": "settings_insiderpage_xaml_insiderpage", "relation": "references", "confidence": "EXTRACTED", "source_file": "Rise Media Player Dev/Settings/InsiderPage.xaml", "source_location": "L2", "weight": 1.0, "context": "x_class"}, {"source": "settings_insiderpage_page", "target": "settings_insiderpage_xaml_insiderpage_expandercontrol_click", "relation": "references", "confidence": "EXTRACTED", "source_file": "Rise Media Player Dev/Settings/InsiderPage.xaml", "source_location": "L20", "weight": 1.0, "context": "event"}, {"source": "settings_insiderpage_xaml_insiderpage", "target": "settings_insiderpage_xaml_insiderpage_expandercontrol_click", "relation": "method", "confidence": "EXTRACTED", "source_file": "Rise Media Player Dev/Settings/InsiderPage.xaml.cs", "source_location": "L17", "weight": 1.0}]}