{"nodes": [{"id": "c_w_rise_rise_media_player_dev_views_albums_albumspage_xaml", "label": "AlbumsPage.xaml", "file_type": "code", "source_file": "Rise Media Player Dev/Views/Albums/AlbumsPage.xaml", "source_location": "L1"}, {"id": "albums_albumspage_mediapagebase", "label": "MediaPageBase", "file_type": "code", "source_file": "Rise Media Player Dev/Views/Albums/AlbumsPage.xaml", "source_location": "L1"}, {"id": "albums_albumspage_xaml_albumspage", "label": "AlbumsPage", "file_type": "code", "source_file": "Rise Media Player Dev/Views/Albums/AlbumsPage.xaml.cs", "source_location": "L17"}, {"id": "albums_albumspage_pageroot", "label": "PageRoot", "file_type": "code", "source_file": "Rise Media Player Dev/Views/Albums/AlbumsPage.xaml", "source_location": "L16"}, {"id": "xaml_mediapagebase", "label": "MediaPageBase", "file_type": "concept", "source_file": "Rise Media Player Dev/Views/Albums/AlbumsPage.xaml", "source_location": "L16"}, {"id": "albums_albumspage_discyonalbum", "label": "DiscyOnAlbum", "file_type": "code", "source_file": "Rise Media Player Dev/Views/Albums/AlbumsPage.xaml", "source_location": "L35"}, {"id": "xaml_teachingtip", "label": "TeachingTip", "file_type": "concept", "source_file": "Rise Media Player Dev/Views/Albums/AlbumsPage.xaml", "source_location": "L35"}, {"id": "albums_albumspage_addtobar", "label": "AddToBar", "file_type": "code", "source_file": "Rise Media Player Dev/Views/Albums/AlbumsPage.xaml", "source_location": "L76"}, {"id": "xaml_menuflyout", "label": "MenuFlyout", "file_type": "concept", "source_file": "Rise Media Player Dev/Views/Albums/AlbumsPage.xaml", "source_location": "L76"}, {"id": "albums_albumspage_xaml_albumspage_addfolders_click", "label": ".AddFolders_Click()", "file_type": "code", "source_file": "Rise Media Player Dev/Views/Albums/AlbumsPage.xaml.cs", "source_location": "L115"}, {"id": "albums_albumspage_maingrid", "label": "MainGrid", "file_type": "code", "source_file": "Rise Media Player Dev/Views/Albums/AlbumsPage.xaml", "source_location": "L194"}, {"id": "xaml_gridview", "label": "GridView", "file_type": "concept", "source_file": "Rise Media Player Dev/Views/Albums/AlbumsPage.xaml", "source_location": "L194"}, {"id": "albums_albumspage_xaml_albumspage_maingrid_itemclick", "label": ".MainGrid_ItemClick()", "file_type": "code", "source_file": "Rise Media Player Dev/Views/Albums/AlbumsPage.xaml.cs", "source_location": "L91"}, {"id": "albums_albumspage_addto", "label": "AddTo", "file_type": "code", "source_file": "Rise Media Player Dev/Views/Albums/AlbumsPage.xaml", "source_location": "L70"}, {"id": "xaml_menuflyoutsubitem", "label": "MenuFlyoutSubItem", "file_type": "concept", "source_file": "Rise Media Player Dev/Views/Albums/AlbumsPage.xaml", "source_location": "L70"}, {"id": "albums_albumspage_xaml_albumspage_askdiscy_click", "label": ".AskDiscy_Click()", "file_type": "code", "source_file": "Rise Media Player Dev/Views/Albums/AlbumsPage.xaml.cs", "source_location": "L110"}, {"id": "binding_gotoartistcommand", "label": "GoToArtistCommand", "file_type": "concept", "source_file": "Rise Media Player Dev/Views/Albums/AlbumsPage.xaml", "source_location": "L271"}, {"id": "albums_albumspage_zoomedoutgrid", "label": "ZoomedOutGrid", "file_type": "code", "source_file": "Rise Media Player Dev/Views/Albums/AlbumsPage.xaml", "source_location": "L286"}, {"id": "albums_albumspage_sortingstates", "label": "SortingStates", "file_type": "code", "source_file": "Rise Media Player Dev/Views/Albums/AlbumsPage.xaml", "source_location": "L295"}, {"id": "xaml_visualstategroup", "label": "VisualStateGroup", "file_type": "concept", "source_file": "Rise Media Player Dev/Views/Albums/AlbumsPage.xaml", "source_location": "L295"}, {"id": "albums_albumspage_nonalphabeticalsorting", "label": "NonAlphabeticalSorting", "file_type": "code", "source_file": "Rise Media Player Dev/Views/Albums/AlbumsPage.xaml", "source_location": "L296"}, {"id": "xaml_visualstate", "label": "VisualState", "file_type": "concept", "source_file": "Rise Media Player Dev/Views/Albums/AlbumsPage.xaml", "source_location": "L296"}, {"id": "albums_albumspage_alphabeticalsorting", "label": "AlphabeticalSorting", "file_type": "code", "source_file": "Rise Media Player Dev/Views/Albums/AlbumsPage.xaml", "source_location": "L296"}], "edges": [{"source": "c_w_rise_rise_media_player_dev_views_albums_albumspage_xaml", "target": "albums_albumspage_mediapagebase", "relation": "contains", "confidence": "EXTRACTED", "source_file": "Rise Media Player Dev/Views/Albums/AlbumsPage.xaml", "source_location": "L1", "weight": 1.0}, {"source": "albums_albumspage_mediapagebase", "target": "albums_albumspage_xaml_albumspage", "relation": "references", "confidence": "EXTRACTED", "source_file": "Rise Media Player Dev/Views/Albums/AlbumsPage.xaml", "source_location": "L2", "weight": 1.0, "context": "x_class"}, {"source": "albums_albumspage_mediapagebase", "target": "albums_albumspage_pageroot", "relation": "contains", "confidence": "EXTRACTED", "source_file": "Rise Media Player Dev/Views/Albums/AlbumsPage.xaml", "source_location": "L16", "weight": 1.0}, {"source": "albums_albumspage_pageroot", "target": "xaml_mediapagebase", "relation": "references", "confidence": "EXTRACTED", "source_file": "Rise Media Player Dev/Views/Albums/AlbumsPage.xaml", "source_location": "L16", "weight": 1.0, "context": "type"}, {"source": "albums_albumspage_mediapagebase", "target": "albums_albumspage_discyonalbum", "relation": "contains", "confidence": "EXTRACTED", "source_file": "Rise Media Player Dev/Views/Albums/AlbumsPage.xaml", "source_location": "L35", "weight": 1.0}, {"source": "albums_albumspage_discyonalbum", "target": "xaml_teachingtip", "relation": "references", "confidence": "EXTRACTED", "source_file": "Rise Media Player Dev/Views/Albums/AlbumsPage.xaml", "source_location": "L35", "weight": 1.0, "context": "type"}, {"source": "albums_albumspage_mediapagebase", "target": "albums_albumspage_addtobar", "relation": "contains", "confidence": "EXTRACTED", "source_file": "Rise Media Player Dev/Views/Albums/AlbumsPage.xaml", "source_location": "L76", "weight": 1.0}, {"source": "albums_albumspage_addtobar", "target": "xaml_menuflyout", "relation": "references", "confidence": "EXTRACTED", "source_file": "Rise Media Player Dev/Views/Albums/AlbumsPage.xaml", "source_location": "L76", "weight": 1.0, "context": "type"}, {"source": "albums_albumspage_mediapagebase", "target": "albums_albumspage_xaml_albumspage_addfolders_click", "relation": "references", "confidence": "EXTRACTED", "source_file": "Rise Media Player Dev/Views/Albums/AlbumsPage.xaml", "source_location": "L185", "weight": 1.0, "context": "event"}, {"source": "albums_albumspage_xaml_albumspage", "target": "albums_albumspage_xaml_albumspage_addfolders_click", "relation": "method", "confidence": "EXTRACTED", "source_file": "Rise Media Player Dev/Views/Albums/AlbumsPage.xaml.cs", "source_location": "L115", "weight": 1.0}, {"source": "albums_albumspage_mediapagebase", "target": "albums_albumspage_maingrid", "relation": "contains", "confidence": "EXTRACTED", "source_file": "Rise Media Player Dev/Views/Albums/AlbumsPage.xaml", "source_location": "L194", "weight": 1.0}, {"source": "albums_albumspage_maingrid", "target": "xaml_gridview", "relation": "references", "confidence": "EXTRACTED", "source_file": "Rise Media Player Dev/Views/Albums/AlbumsPage.xaml", "source_location": "L194", "weight": 1.0, "context": "type"}, {"source": "albums_albumspage_maingrid", "target": "albums_albumspage_xaml_albumspage_maingrid_itemclick", "relation": "references", "confidence": "EXTRACTED", "source_file": "Rise Media Player Dev/Views/Albums/AlbumsPage.xaml", "source_location": "L199", "weight": 1.0, "context": "event"}, {"source": "albums_albumspage_xaml_albumspage", "target": "albums_albumspage_xaml_albumspage_maingrid_itemclick", "relation": "method", "confidence": "EXTRACTED", "source_file": "Rise Media Player Dev/Views/Albums/AlbumsPage.xaml.cs", "source_location": "L91", "weight": 1.0}, {"source": "albums_albumspage_mediapagebase", "target": "albums_albumspage_addto", "relation": "contains", "confidence": "EXTRACTED", "source_file": "Rise Media Player Dev/Views/Albums/AlbumsPage.xaml", "source_location": "L70", "weight": 1.0}, {"source": "albums_albumspage_addto", "target": "xaml_menuflyoutsubitem", "relation": "references", "confidence": "EXTRACTED", "source_file": "Rise Media Player Dev/Views/Albums/AlbumsPage.xaml", "source_location": "L70", "weight": 1.0, "context": "type"}, {"source": "albums_albumspage_mediapagebase", "target": "albums_albumspage_xaml_albumspage_askdiscy_click", "relation": "references", "confidence": "EXTRACTED", "source_file": "Rise Media Player Dev/Views/Albums/AlbumsPage.xaml", "source_location": "L244", "weight": 1.0, "context": "event"}, {"source": "albums_albumspage_xaml_albumspage", "target": "albums_albumspage_xaml_albumspage_askdiscy_click", "relation": "method", "confidence": "EXTRACTED", "source_file": "Rise Media Player Dev/Views/Albums/AlbumsPage.xaml.cs", "source_location": "L110", "weight": 1.0}, {"source": "albums_albumspage_mediapagebase", "target": "binding_gotoartistcommand", "relation": "references", "confidence": "EXTRACTED", "source_file": "Rise Media Player Dev/Views/Albums/AlbumsPage.xaml", "source_location": "L271", "weight": 1.0, "context": "binding_path"}, {"source": "albums_albumspage_mediapagebase", "target": "albums_albumspage_zoomedoutgrid", "relation": "contains", "confidence": "EXTRACTED", "source_file": "Rise Media Player Dev/Views/Albums/AlbumsPage.xaml", "source_location": "L286", "weight": 1.0}, {"source": "albums_albumspage_zoomedoutgrid", "target": "xaml_gridview", "relation": "references", "confidence": "EXTRACTED", "source_file": "Rise Media Player Dev/Views/Albums/AlbumsPage.xaml", "source_location": "L286", "weight": 1.0, "context": "type"}, {"source": "albums_albumspage_mediapagebase", "target": "albums_albumspage_sortingstates", "relation": "contains", "confidence": "EXTRACTED", "source_file": "Rise Media Player Dev/Views/Albums/AlbumsPage.xaml", "source_location": "L295", "weight": 1.0}, {"source": "albums_albumspage_sortingstates", "target": "xaml_visualstategroup", "relation": "references", "confidence": "EXTRACTED", "source_file": "Rise Media Player Dev/Views/Albums/AlbumsPage.xaml", "source_location": "L295", "weight": 1.0, "context": "type"}, {"source": "albums_albumspage_mediapagebase", "target": "albums_albumspage_nonalphabeticalsorting", "relation": "contains", "confidence": "EXTRACTED", "source_file": "Rise Media Player Dev/Views/Albums/AlbumsPage.xaml", "source_location": "L296", "weight": 1.0}, {"source": "albums_albumspage_nonalphabeticalsorting", "target": "xaml_visualstate", "relation": "references", "confidence": "EXTRACTED", "source_file": "Rise Media Player Dev/Views/Albums/AlbumsPage.xaml", "source_location": "L296", "weight": 1.0, "context": "type"}, {"source": "albums_albumspage_mediapagebase", "target": "albums_albumspage_alphabeticalsorting", "relation": "contains", "confidence": "EXTRACTED", "source_file": "Rise Media Player Dev/Views/Albums/AlbumsPage.xaml", "source_location": "L296", "weight": 1.0}, {"source": "albums_albumspage_alphabeticalsorting", "target": "xaml_visualstate", "relation": "references", "confidence": "EXTRACTED", "source_file": "Rise Media Player Dev/Views/Albums/AlbumsPage.xaml", "source_location": "L296", "weight": 1.0, "context": "type"}]}