{"nodes": [{"id": "c_w_rise_rise_common_attached_gridhelper_cs", "label": "GridHelper.cs", "file_type": "code", "source_file": "Rise.Common/Attached/GridHelper.cs", "source_location": "L1"}, {"id": "attached_gridhelper_rise_common_attached", "label": "Rise.Common.Attached", "file_type": "code", "source_file": "Rise.Common/Attached/GridHelper.cs", "source_location": "L4"}, {"id": "attached_gridhelper_gridhelper", "label": "GridHelper", "file_type": "code", "source_file": "Rise.Common/Attached/GridHelper.cs", "source_location": "L10"}, {"id": "dependencyobject", "label": "DependencyObject", "file_type": "code", "source_file": "", "source_location": ""}, {"id": "dependencyproperty", "label": "DependencyProperty", "file_type": "code", "source_file": "", "source_location": ""}, {"id": "attached_gridhelper_gridhelper_getrowheights", "label": ".GetRowHeights()", "file_type": "code", "source_file": "Rise.Common/Attached/GridHelper.cs", "source_location": "L20"}, {"id": "grid", "label": "Grid", "file_type": "code", "source_file": "", "source_location": ""}, {"id": "attached_gridhelper_gridhelper_setrowheights", "label": ".SetRowHeights()", "file_type": "code", "source_file": "Rise.Common/Attached/GridHelper.cs", "source_location": "L22"}, {"id": "attached_gridhelper_gridhelper_getcolumnwidths", "label": ".GetColumnWidths()", "file_type": "code", "source_file": "Rise.Common/Attached/GridHelper.cs", "source_location": "L33"}, {"id": "attached_gridhelper_gridhelper_setcolumnwidths", "label": ".SetColumnWidths()", "file_type": "code", "source_file": "Rise.Common/Attached/GridHelper.cs", "source_location": "L35"}, {"id": "attached_gridhelper_gridhelper_rowheightschanged", "label": ".RowHeightsChanged()", "file_type": "code", "source_file": "Rise.Common/Attached/GridHelper.cs", "source_location": "L38"}, {"id": "dependencypropertychangedeventargs", "label": "DependencyPropertyChangedEventArgs", "file_type": "code", "source_file": "", "source_location": ""}, {"id": "attached_gridhelper_gridhelper_columnwidthschanged", "label": ".ColumnWidthsChanged()", "file_type": "code", "source_file": "Rise.Common/Attached/GridHelper.cs", "source_location": "L55"}, {"id": "attached_gridhelper_gridhelper_adddefinition", "label": ".AddDefinition()", "file_type": "code", "source_file": "Rise.Common/Attached/GridHelper.cs", "source_location": "L72"}], "edges": [{"source": "c_w_rise_rise_common_attached_gridhelper_cs", "target": "xaml", "relation": "imports", "context": "import", "confidence": "EXTRACTED", "source_file": "Rise.Common/Attached/GridHelper.cs", "source_location": "L1", "weight": 1.0}, {"source": "c_w_rise_rise_common_attached_gridhelper_cs", "target": "controls", "relation": "imports", "context": "import", "confidence": "EXTRACTED", "source_file": "Rise.Common/Attached/GridHelper.cs", "source_location": "L2", "weight": 1.0}, {"source": "c_w_rise_rise_common_attached_gridhelper_cs", "target": "attached_gridhelper_rise_common_attached", "relation": "contains", "confidence": "EXTRACTED", "source_file": "Rise.Common/Attached/GridHelper.cs", "source_location": "L4", "weight": 1.0}, {"source": "c_w_rise_rise_common_attached_gridhelper_cs", "target": "attached_gridhelper_gridhelper", "relation": "contains", "confidence": "EXTRACTED", "source_file": "Rise.Common/Attached/GridHelper.cs", "source_location": "L10", "weight": 1.0}, {"source": "attached_gridhelper_gridhelper", "target": "dependencyobject", "relation": "inherits", "confidence": "EXTRACTED", "source_file": "Rise.Common/Attached/GridHelper.cs", "source_location": "L10", "weight": 1.0}, {"source": "attached_gridhelper_gridhelper", "target": "dependencyproperty", "relation": "references", "confidence": "EXTRACTED", "source_file": "Rise.Common/Attached/GridHelper.cs", "source_location": "L16", "weight": 1.0, "context": "field"}, {"source": "attached_gridhelper_gridhelper", "target": "attached_gridhelper_gridhelper_getrowheights", "relation": "method", "confidence": "EXTRACTED", "source_file": "Rise.Common/Attached/GridHelper.cs", "source_location": "L20", "weight": 1.0}, {"source": "attached_gridhelper_gridhelper_getrowheights", "target": "grid", "relation": "references", "confidence": "EXTRACTED", "source_file": "Rise.Common/Attached/GridHelper.cs", "source_location": "L20", "weight": 1.0, "context": "parameter_type"}, {"source": "attached_gridhelper_gridhelper", "target": "attached_gridhelper_gridhelper_setrowheights", "relation": "method", "confidence": "EXTRACTED", "source_file": "Rise.Common/Attached/GridHelper.cs", "source_location": "L22", "weight": 1.0}, {"source": "attached_gridhelper_gridhelper_setrowheights", "target": "grid", "relation": "references", "confidence": "EXTRACTED", "source_file": "Rise.Common/Attached/GridHelper.cs", "source_location": "L22", "weight": 1.0, "context": "parameter_type"}, {"source": "attached_gridhelper_gridhelper", "target": "dependencyproperty", "relation": "references", "confidence": "EXTRACTED", "source_file": "Rise.Common/Attached/GridHelper.cs", "source_location": "L29", "weight": 1.0, "context": "field"}, {"source": "attached_gridhelper_gridhelper", "target": "attached_gridhelper_gridhelper_getcolumnwidths", "relation": "method", "confidence": "EXTRACTED", "source_file": "Rise.Common/Attached/GridHelper.cs", "source_location": "L33", "weight": 1.0}, {"source": "attached_gridhelper_gridhelper_getcolumnwidths", "target": "grid", "relation": "references", "confidence": "EXTRACTED", "source_file": "Rise.Common/Attached/GridHelper.cs", "source_location": "L33", "weight": 1.0, "context": "parameter_type"}, {"source": "attached_gridhelper_gridhelper", "target": "attached_gridhelper_gridhelper_setcolumnwidths", "relation": "method", "confidence": "EXTRACTED", "source_file": "Rise.Common/Attached/GridHelper.cs", "source_location": "L35", "weight": 1.0}, {"source": "attached_gridhelper_gridhelper_setcolumnwidths", "target": "grid", "relation": "references", "confidence": "EXTRACTED", "source_file": "Rise.Common/Attached/GridHelper.cs", "source_location": "L35", "weight": 1.0, "context": "parameter_type"}, {"source": "attached_gridhelper_gridhelper", "target": "attached_gridhelper_gridhelper_rowheightschanged", "relation": "method", "confidence": "EXTRACTED", "source_file": "Rise.Common/Attached/GridHelper.cs", "source_location": "L38", "weight": 1.0}, {"source": "attached_gridhelper_gridhelper_rowheightschanged", "target": "dependencyobject", "relation": "references", "confidence": "EXTRACTED", "source_file": "Rise.Common/Attached/GridHelper.cs", "source_location": "L38", "weight": 1.0, "context": "parameter_type"}, {"source": "attached_gridhelper_gridhelper_rowheightschanged", "target": "dependencypropertychangedeventargs", "relation": "references", "confidence": "EXTRACTED", "source_file": "Rise.Common/Attached/GridHelper.cs", "source_location": "L38", "weight": 1.0, "context": "parameter_type"}, {"source": "attached_gridhelper_gridhelper", "target": "attached_gridhelper_gridhelper_columnwidthschanged", "relation": "method", "confidence": "EXTRACTED", "source_file": "Rise.Common/Attached/GridHelper.cs", "source_location": "L55", "weight": 1.0}, {"source": "attached_gridhelper_gridhelper_columnwidthschanged", "target": "dependencyobject", "relation": "references", "confidence": "EXTRACTED", "source_file": "Rise.Common/Attached/GridHelper.cs", "source_location": "L55", "weight": 1.0, "context": "parameter_type"}, {"source": "attached_gridhelper_gridhelper_columnwidthschanged", "target": "dependencypropertychangedeventargs", "relation": "references", "confidence": "EXTRACTED", "source_file": "Rise.Common/Attached/GridHelper.cs", "source_location": "L55", "weight": 1.0, "context": "parameter_type"}, {"source": "attached_gridhelper_gridhelper", "target": "attached_gridhelper_gridhelper_adddefinition", "relation": "method", "confidence": "EXTRACTED", "source_file": "Rise.Common/Attached/GridHelper.cs", "source_location": "L72", "weight": 1.0}, {"source": "attached_gridhelper_gridhelper_adddefinition", "target": "grid", "relation": "references", "confidence": "EXTRACTED", "source_file": "Rise.Common/Attached/GridHelper.cs", "source_location": "L72", "weight": 1.0, "context": "parameter_type"}, {"source": "attached_gridhelper_gridhelper_rowheightschanged", "target": "attached_gridhelper_gridhelper_adddefinition", "relation": "calls", "context": "call", "confidence": "EXTRACTED", "source_file": "Rise.Common/Attached/GridHelper.cs", "source_location": "L52", "weight": 1.0}, {"source": "attached_gridhelper_gridhelper_columnwidthschanged", "target": "attached_gridhelper_gridhelper_adddefinition", "relation": "calls", "context": "call", "confidence": "EXTRACTED", "source_file": "Rise.Common/Attached/GridHelper.cs", "source_location": "L69", "weight": 1.0}], "raw_calls": [{"caller_nid": "attached_gridhelper_gridhelper_getrowheights", "callee": "GetValue", "is_member_call": true, "source_file": "C:\\w\\Rise\\Rise.Common\\Attached\\GridHelper.cs", "source_location": "L21", "receiver": null}, {"caller_nid": "attached_gridhelper_gridhelper_setrowheights", "callee": "SetValue", "is_member_call": true, "source_file": "C:\\w\\Rise\\Rise.Common\\Attached\\GridHelper.cs", "source_location": "L23", "receiver": null}, {"caller_nid": "attached_gridhelper_gridhelper_getcolumnwidths", "callee": "GetValue", "is_member_call": true, "source_file": "C:\\w\\Rise\\Rise.Common\\Attached\\GridHelper.cs", "source_location": "L34", "receiver": null}, {"caller_nid": "attached_gridhelper_gridhelper_setcolumnwidths", "callee": "SetValue", "is_member_call": true, "source_file": "C:\\w\\Rise\\Rise.Common\\Attached\\GridHelper.cs", "source_location": "L36", "receiver": null}, {"caller_nid": "attached_gridhelper_gridhelper_rowheightschanged", "callee": "Clear", "is_member_call": true, "source_file": "C:\\w\\Rise\\Rise.Common\\Attached\\GridHelper.cs", "source_location": "L44", "receiver": null}, {"caller_nid": "attached_gridhelper_gridhelper_rowheightschanged", "callee": "ToString", "is_member_call": true, "source_file": "C:\\w\\Rise\\Rise.Common\\Attached\\GridHelper.cs", "source_location": "L46", "receiver": null}, {"caller_nid": "attached_gridhelper_gridhelper_rowheightschanged", "callee": "IsNullOrEmpty", "is_member_call": true, "source_file": "C:\\w\\Rise\\Rise.Common\\Attached\\GridHelper.cs", "source_location": "L47", "receiver": null}, {"caller_nid": "attached_gridhelper_gridhelper_rowheightschanged", "callee": "Split", "is_member_call": true, "source_file": "C:\\w\\Rise\\Rise.Common\\Attached\\GridHelper.cs", "source_location": "L50", "receiver": null}, {"caller_nid": "attached_gridhelper_gridhelper_columnwidthschanged", "callee": "Clear", "is_member_call": true, "source_file": "C:\\w\\Rise\\Rise.Common\\Attached\\GridHelper.cs", "source_location": "L61", "receiver": null}, {"caller_nid": "attached_gridhelper_gridhelper_columnwidthschanged", "callee": "ToString", "is_member_call": true, "source_file": "C:\\w\\Rise\\Rise.Common\\Attached\\GridHelper.cs", "source_location": "L63", "receiver": null}, {"caller_nid": "attached_gridhelper_gridhelper_columnwidthschanged", "callee": "IsNullOrEmpty", "is_member_call": true, "source_file": "C:\\w\\Rise\\Rise.Common\\Attached\\GridHelper.cs", "source_location": "L64", "receiver": null}, {"caller_nid": "attached_gridhelper_gridhelper_columnwidthschanged", "callee": "Split", "is_member_call": true, "source_file": "C:\\w\\Rise\\Rise.Common\\Attached\\GridHelper.cs", "source_location": "L67", "receiver": null}, {"caller_nid": "attached_gridhelper_gridhelper_adddefinition", "callee": "EndsWith", "is_member_call": true, "source_file": "C:\\w\\Rise\\Rise.Common\\Attached\\GridHelper.cs", "source_location": "L79", "receiver": null}, {"caller_nid": "attached_gridhelper_gridhelper_adddefinition", "callee": "Replace", "is_member_call": true, "source_file": "C:\\w\\Rise\\Rise.Common\\Attached\\GridHelper.cs", "source_location": "L81", "receiver": null}, {"caller_nid": "attached_gridhelper_gridhelper_adddefinition", "callee": "IsNullOrEmpty", "is_member_call": true, "source_file": "C:\\w\\Rise\\Rise.Common\\Attached\\GridHelper.cs", "source_location": "L82", "receiver": null}, {"caller_nid": "attached_gridhelper_gridhelper_adddefinition", "callee": "Parse", "is_member_call": true, "source_file": "C:\\w\\Rise\\Rise.Common\\Attached\\GridHelper.cs", "source_location": "L85", "receiver": null}, {"caller_nid": "attached_gridhelper_gridhelper_adddefinition", "callee": "Parse", "is_member_call": true, "source_file": "C:\\w\\Rise\\Rise.Common\\Attached\\GridHelper.cs", "source_location": "L90", "receiver": null}, {"caller_nid": "attached_gridhelper_gridhelper_adddefinition", "callee": "Add", "is_member_call": true, "source_file": "C:\\w\\Rise\\Rise.Common\\Attached\\GridHelper.cs", "source_location": "L97", "receiver": null}, {"caller_nid": "attached_gridhelper_gridhelper_adddefinition", "callee": "Add", "is_member_call": true, "source_file": "C:\\w\\Rise\\Rise.Common\\Attached\\GridHelper.cs", "source_location": "L102", "receiver": null}]}